ai_assistant/__init__.py
ai_assistant/ai_assistant.py
ai_assistant/piper_helper.py
ai_assistant_sm-0.0.2.dist-info/METADATA
ai_assistant_sm-0.0.2.dist-info/WHEEL
ai_assistant_sm-0.0.2.dist-info/top_level.txt
ai_assistant_sm-0.0.2.dist-info/RECORD
